CHANGES.txt
COPYING.txt
MANIFEST.in
README.txt
TODO.txt
about.txt
development.ini
production.ini
setup.cfg
setup.py
misc/__init__.py
misc/wingdbstub.py
pyGallerid/__init__.py
pyGallerid.egg-info/PKG-INFO
pyGallerid.egg-info/SOURCES.txt
pyGallerid.egg-info/dependency_links.txt
pyGallerid.egg-info/entry_points.txt
pyGallerid.egg-info/not-zip-safe
pyGallerid.egg-info/requires.txt
pyGallerid.egg-info/top_level.txt
pyGallerid/evolve/__init__.py
pyGallerid/evolve/evolve1.py
pyGallerid/models/__init__.py
pyGallerid/models/gallery.py
pyGallerid/models/user.py
pyGallerid/scripts/__init__.py
pyGallerid/scripts/import_pictures.py
pyGallerid/scripts/init_gallery.py
pyGallerid/static/favicon.ico
pyGallerid/static/footerbg.png
pyGallerid/static/headerbg.png
pyGallerid/static/ie6.css
pyGallerid/static/middlebg.png
pyGallerid/static/pylons.css
pyGallerid/static/pyramid-small.png
pyGallerid/static/pyramid.png
pyGallerid/static/transparent.gif
pyGallerid/static/css/global.css
pyGallerid/static/css/global_ie.css
pyGallerid/static/css/pyGallerid.css
pyGallerid/static/img/spacer.gif
pyGallerid/static/js/pyGallerid.js
pyGallerid/static/js/pyGalleridEditing.js
pyGallerid/static/js/galleria/galleria-1.2.6.min.js
pyGallerid/static/js/galleria/plugins/flickr/flickr-demo.html
pyGallerid/static/js/galleria/plugins/flickr/flickr-loader.gif
pyGallerid/static/js/galleria/plugins/flickr/galleria.flickr.js
pyGallerid/static/js/galleria/plugins/flickr/galleria.flickr.min.js
pyGallerid/static/js/galleria/plugins/flickr/loader.gif
pyGallerid/static/js/galleria/plugins/history/galleria.history.js
pyGallerid/static/js/galleria/plugins/history/galleria.history.min.js
pyGallerid/static/js/galleria/plugins/history/history-demo.html
pyGallerid/static/js/galleria/plugins/picasa/galleria.picasa.js
pyGallerid/static/js/galleria/plugins/picasa/galleria.picasa.min.js
pyGallerid/static/js/galleria/plugins/picasa/loader.gif
pyGallerid/static/js/galleria/plugins/picasa/picasa-demo.html
pyGallerid/static/js/galleria/themes/classic/classic-demo.html
pyGallerid/static/js/galleria/themes/classic/classic-loader.gif
pyGallerid/static/js/galleria/themes/classic/classic-map.png
pyGallerid/static/js/galleria/themes/classic/galleria.classic.css
