Metadata-Version: 1.0
Name: pyGallerid
Version: 0.2
Summary: python web photo gallery based on pyramid
Home-page: https://github.com/bennihepp/pyGallerid
Author: Benjamin Hepp
Author-email: benjamin.hepp@gmail.com
License: BSD
Keywords: web pyramid pylons gallery photo
Platform: UNKNOWN
Classifier: Operating System :: OS Independent
Classifier: License :: OSI Approved :: BSD License
Classifier: Programming Language :: Python
Classifier: Development Status :: 4 - Beta
Classifier: Framework :: Pylons
Classifier: Topic :: Internet :: WWW/HTTP
Classifier: Topic :: Internet :: WWW/HTTP :: WSGI :: Application
